{
  "_comment": "Single source of truth for all template ids. Append-only — changing order shifts ids. Id 0 reserved as UNSPECIFIED; sequential u16 assigned from 1 in declaration order.",
  "_design_doc": "docs/plans/2026-04-25-template-id-codegen-design.md",

  "_tower_stats_doc": "Tower stats live here as the single source of truth. omoba-template-ids/build.rs reads them and emits TOWER_<NAME>_STATS const + tower_stats(id) lookup, used by base_content tower scripts. 改完 stats 重 build script DLL 即生效，不需動 host 程式碼或 map.json。",
  "towers": [
    {
      "id": "tower_dart", "display_name": "Dart Monkey",
      "atk": 10.0, "asd_interval": 0.8, "range": 350.0, "bullet_speed": 1200.0,
      "splash_radius": 0.0, "hit_radius": 0.0,
      "slow_factor": 0.0, "slow_duration": 0.0,
      "cost": 200, "footprint": 10.0, "hp": 1.0, "turn_speed_deg": 360.0
    },
    {
      "id": "tower_tack", "display_name": "Tack Shooter",
      "atk": 8.0, "asd_interval": 1.2, "range": 380.0, "bullet_speed": 1400.0,
      "splash_radius": 0.0, "hit_radius": 80.0,
      "slow_factor": 0.0, "slow_duration": 0.0,
      "cost": 400, "footprint": 10.0, "hp": 1.0, "turn_speed_deg": 3600.0
    },
    {
      "id": "tower_bomb", "display_name": "Bomb Shooter",
      "atk": 30.0, "asd_interval": 1.5, "range": 400.0, "bullet_speed": 900.0,
      "splash_radius": 200.0, "hit_radius": 0.0,
      "slow_factor": 0.0, "slow_duration": 0.0,
      "cost": 650, "footprint": 12.5, "hp": 1.0, "turn_speed_deg": 360.0
    },
    {
      "id": "tower_ice", "display_name": "Ice Monkey",
      "atk": 3.0, "asd_interval": 1.5, "range": 180.0, "bullet_speed": 600.0,
      "splash_radius": 90.0, "hit_radius": 0.0,
      "slow_factor": 0.5, "slow_duration": 2.0,
      "cost": 400, "footprint": 10.0, "hp": 1.0, "turn_speed_deg": 360.0
    }
  ],

  "heroes": [
    {
      "id": "saika_magoichi",
      "display_name": "雜賀孫市",
      "title": "千里狙擊手",
      "background": "雜賀眾的領袖，以精準的遠程射擊聞名於戰國時代",
      "abilities": ["sniper_mode", "saika_reinforcements", "rain_iron_cannon", "three_stage_technique"],
      "strength": 18,
      "agility": 28,
      "intelligence": 16,
      "primary_attribute": "agility",
      "attack_range": 900.0,
      "base_damage": 52,
      "base_armor": 1.5,
      "base_hp": 580,
      "base_mana": 300,
      "move_speed": 320.0,
      "turn_speed": 180.0,
      "level_growth": {
        "strength_per_level": 1.8,
        "agility_per_level": 3.2,
        "intelligence_per_level": 1.6,
        "damage_per_level": 2.8,
        "hp_per_level": 58.0,
        "mana_per_level": 26.0
      }
    },
    {
      "id": "date_masamune",
      "display_name": "伊達政宗",
      "title": "獨眼龍",
      "background": "奧州的霸主，以炎之鬥技與火繩銃聞名",
      "abilities": ["flame_blade", "fire_dash", "flame_assault", "matchlock_gun"],
      "strength": 26,
      "agility": 22,
      "intelligence": 14,
      "primary_attribute": "strength",
      "attack_range": 250.0,
      "base_damage": 60,
      "base_armor": 2.5,
      "base_hp": 680,
      "base_mana": 240,
      "move_speed": 310.0,
      "turn_speed": 200.0,
      "level_growth": {
        "strength_per_level": 3.0,
        "agility_per_level": 1.8,
        "intelligence_per_level": 1.4,
        "damage_per_level": 3.2,
        "hp_per_level": 68.0,
        "mana_per_level": 22.0
      }
    }
  ],

  "_ability_data_doc": "Ability 完整數值 — extras 每 key 必須是長度 = max_level 的 f32 陣列。omoba-template-ids/build.rs 編成 ABILITY_<NAME>_CONST: AbilityConst const + ability_const(id) lookup。base_content ability scripts 用 build_ability_def_from_const 攤成完整 AbilityDef。",
  "abilities": [
    {
      "id": "sniper_mode",
      "display_name": "狙擊模式",
      "description": "切換到狙擊模式，增加射程和傷害，但降低攻擊速度和移動速度。",
      "ability_type": "toggle",
      "target_type": "none",
      "cast_type": "instant",
      "max_level": 4,
      "levels": [
        { "cooldown": 0.0, "mana_cost": 0.0, "cast_time": 0.0, "range": 0.0 },
        { "cooldown": 0.0, "mana_cost": 0.0, "cast_time": 0.0, "range": 0.0 },
        { "cooldown": 0.0, "mana_cost": 0.0, "cast_time": 0.0, "range": 0.0 },
        { "cooldown": 0.0, "mana_cost": 0.0, "cast_time": 0.0, "range": 0.0 }
      ],
      "extras": {
        "range_bonus":          [100.0, 200.0, 300.0, 400.0],
        "damage_bonus":         [0.15, 0.25, 0.35, 0.45],
        "attack_speed_penalty": [-0.30, -0.30, -0.30, -0.30],
        "move_speed_penalty":   [-0.50, -0.50, -0.50, -0.50],
        "accuracy_bonus":       [0.10, 0.10, 0.10, 0.10]
      }
    },
    {
      "id": "saika_reinforcements",
      "display_name": "雜賀援軍",
      "description": "在目標位置召喚雜賀鐵炮兵協助作戰。",
      "ability_type": "active",
      "target_type": "point",
      "cast_type": "instant",
      "max_level": 4,
      "levels": [
        { "cooldown": 27.0, "mana_cost": 90.0, "cast_time": 0.5, "range": 800.0 },
        { "cooldown": 26.0, "mana_cost": 90.0, "cast_time": 0.5, "range": 800.0 },
        { "cooldown": 25.0, "mana_cost": 90.0, "cast_time": 0.5, "range": 800.0 },
        { "cooldown": 24.0, "mana_cost": 90.0, "cast_time": 0.5, "range": 800.0 }
      ],
      "extras": {
        "summon_count":        [2.0, 4.0, 6.0, 8.0],
        "duration":            [45.0, 50.0, 55.0, 60.0],
        "row_spacing":         [60.0, 60.0, 60.0, 60.0],
        "col_spacing":         [60.0, 60.0, 60.0, 60.0],
        "front_row_distance":  [120.0, 120.0, 120.0, 120.0],
        "formation_radius":    [100.0, 100.0, 100.0, 100.0],
        "gunner_hp":           [350.0, 400.0, 450.0, 500.0],
        "gunner_damage":       [50.0, 60.0, 70.0, 80.0]
      }
    },
    {
      "id": "rain_iron_cannon",
      "display_name": "雨鐵砲",
      "description": "被動：普攻命中時以受擊點為中心、朝攻擊方向 90° 扇形 150 半徑對範圍內所有單位造成 15/25/35/45% 攻擊力的真實傷害。",
      "ability_type": "passive",
      "target_type": "none",
      "cast_type": "instant",
      "max_level": 4,
      "levels": [
        { "cooldown": 0.0, "mana_cost": 0.0, "cast_time": 0.0, "range": 0.0 },
        { "cooldown": 0.0, "mana_cost": 0.0, "cast_time": 0.0, "range": 0.0 },
        { "cooldown": 0.0, "mana_cost": 0.0, "cast_time": 0.0, "range": 0.0 },
        { "cooldown": 0.0, "mana_cost": 0.0, "cast_time": 0.0, "range": 0.0 }
      ],
      "extras": {
        "true_damage_pct":   [0.15, 0.25, 0.35, 0.45],
        "aoe_radius":        [150.0, 150.0, 150.0, 150.0],
        "arc_half_angle_rad":[0.7853982, 0.7853982, 0.7853982, 0.7853982]
      }
    },
    {
      "id": "three_stage_technique",
      "display_name": "三段擊",
      "description": "變身 5 秒：攻擊力 +200%，普攻特效改為連發 3 發子彈（只判定 1 次傷害），身上有紅色變身特效。",
      "ability_type": "active",
      "target_type": "none",
      "cast_type": "instant",
      "max_level": 4,
      "levels": [
        { "cooldown": 15.0, "mana_cost": 80.0,  "cast_time": 0.0, "range": 0.0 },
        { "cooldown": 13.0, "mana_cost": 90.0,  "cast_time": 0.0, "range": 0.0 },
        { "cooldown": 11.0, "mana_cost": 100.0, "cast_time": 0.0, "range": 0.0 },
        { "cooldown": 9.0,  "mana_cost": 110.0, "cast_time": 0.0, "range": 0.0 }
      ],
      "extras": {
        "duration":         [5.0, 5.0, 5.0, 5.0],
        "atk_bonus_pct":    [2.0, 2.0, 2.0, 2.0],
        "multi_shot_count": [3.0, 3.0, 3.0, 3.0]
      }
    },
    {
      "id": "flame_blade",
      "display_name": "炎刃",
      "description": "往前方揮出一刀，對單體或範圍目標造成大量火焰傷害。",
      "ability_type": "active",
      "target_type": "point",
      "cast_type": "instant",
      "max_level": 4,
      "levels": [
        { "cooldown": 10.0, "mana_cost": 100.0, "cast_time": 0.0, "range": 1100.0 },
        { "cooldown": 10.0, "mana_cost": 120.0, "cast_time": 0.0, "range": 1100.0 },
        { "cooldown": 10.0, "mana_cost": 140.0, "cast_time": 0.0, "range": 1100.0 },
        { "cooldown": 10.0, "mana_cost": 160.0, "cast_time": 0.0, "range": 1100.0 }
      ],
      "extras": {
        "damage":       [200.0, 250.0, 300.0, 350.0],
        "swipe_radius": [100.0, 100.0, 100.0, 100.0]
      }
    },
    {
      "id": "fire_dash",
      "display_name": "火焰衝擊",
      "description": "往前衝刺，沿路對敵人造成火焰傷害。",
      "ability_type": "active",
      "target_type": "point",
      "cast_type": "instant",
      "max_level": 4,
      "levels": [
        { "cooldown": 30.0, "mana_cost": 80.0,  "cast_time": 0.0, "range": 900.0 },
        { "cooldown": 30.0, "mana_cost": 100.0, "cast_time": 0.0, "range": 1000.0 },
        { "cooldown": 30.0, "mana_cost": 120.0, "cast_time": 0.0, "range": 1100.0 },
        { "cooldown": 30.0, "mana_cost": 140.0, "cast_time": 0.0, "range": 1200.0 }
      ],
      "extras": {
        "damage_per_tick": [50.0, 60.0, 70.0, 80.0],
        "dash_duration":   [0.5, 0.5, 0.5, 0.5],
        "speed_bonus":     [2.0, 2.0, 2.0, 2.0],
        "dash_width":      [150.0, 150.0, 150.0, 150.0]
      }
    },
    {
      "id": "flame_assault",
      "display_name": "炎襲",
      "description": "施展一道巨型火焰，對範圍內敵人造成傷害並暈眩。",
      "ability_type": "ultimate",
      "target_type": "point",
      "cast_type": "instant",
      "max_level": 4,
      "levels": [
        { "cooldown": 14.0, "mana_cost": 120.0, "cast_time": 0.0, "range": 700.0 },
        { "cooldown": 14.0, "mana_cost": 140.0, "cast_time": 0.0, "range": 700.0 },
        { "cooldown": 14.0, "mana_cost": 160.0, "cast_time": 0.0, "range": 700.0 },
        { "cooldown": 14.0, "mana_cost": 180.0, "cast_time": 0.0, "range": 700.0 }
      ],
      "extras": {
        "damage":        [200.0, 300.0, 400.0, 500.0],
        "stun_duration": [0.3, 0.6, 0.9, 1.2],
        "radius":        [500.0, 500.0, 500.0, 500.0]
      }
    },
    {
      "id": "matchlock_gun",
      "display_name": "火繩銃",
      "description": "將武器變身火繩銃，增加攻擊距離與傷害，攻擊時有機率暈眩敵人。持續 45 秒。",
      "ability_type": "active",
      "target_type": "none",
      "cast_type": "instant",
      "max_level": 3,
      "levels": [
        { "cooldown": 110.0, "mana_cost": 260.0, "cast_time": 0.0, "range": 0.0 },
        { "cooldown": 110.0, "mana_cost": 310.0, "cast_time": 0.0, "range": 0.0 },
        { "cooldown": 110.0, "mana_cost": 360.0, "cast_time": 0.0, "range": 0.0 }
      ],
      "extras": {
        "duration":      [45.0, 45.0, 45.0],
        "range_bonus":   [700.0, 800.0, 900.0],
        "damage_bonus":  [90.0, 130.0, 170.0],
        "stun_chance":   [0.87, 0.87, 0.87],
        "stun_duration": [0.1, 0.2, 0.3]
      }
    }
  ],

  "buffs": [
    { "id": "stun",        "display_name": "暈眩" },
    { "id": "slow",        "display_name": "減速" },
    { "id": "burn",        "display_name": "燃燒" },
    { "id": "sniper_mode", "display_name": "狙擊姿態" },
    { "id": "three_stage", "display_name": "三段擊" }
  ],

  "summons": [
    {
      "id": "saika_gunner",
      "display_name": "雜賀鐵炮兵",
      "hp": 400.0,
      "damage": 45.0,
      "duration": 60.0,
      "move_speed": 320.0
    }
  ],

  "creeps": [
    {
      "id": "training_mage", "display_name": "訓練法師",
      "hp": 320.0, "armor": 0.5, "magic_resistance": 15.0,
      "damage": 45.0, "attack_range": 550.0, "move_speed": 285.0,
      "enemy_type": "caster", "ai_type": "defensive",
      "exp_reward": 80, "gold_reward": 45
    },
    {
      "id": "fire_mage", "display_name": "火焰法師",
      "hp": 420.0, "armor": 1.0, "magic_resistance": 20.0,
      "damage": 55.0, "attack_range": 600.0, "move_speed": 290.0,
      "enemy_type": "caster", "ai_type": "aggressive",
      "exp_reward": 100, "gold_reward": 60
    },
    {
      "id": "great_mage", "display_name": "大法師",
      "hp": 1500.0, "armor": 3.0, "magic_resistance": 35.0,
      "damage": 85.0, "attack_range": 700.0, "move_speed": 300.0,
      "enemy_type": "boss", "ai_type": "aggressive",
      "exp_reward": 400, "gold_reward": 200
    },
    {
      "id": "practice_dummy", "display_name": "練習假人",
      "hp": 50.0, "armor": 0.0, "magic_resistance": 0.0,
      "damage": 0.0, "attack_range": 0.0, "move_speed": 0.0,
      "enemy_type": "melee", "ai_type": "passive",
      "exp_reward": 0, "gold_reward": 5
    },
    {
      "id": "moving_target", "display_name": "移動靶",
      "hp": 75.0, "armor": 0.0, "magic_resistance": 0.0,
      "damage": 0.0, "attack_range": 0.0, "move_speed": 150.0,
      "enemy_type": "melee", "ai_type": "passive",
      "exp_reward": 0, "gold_reward": 8
    },
    {
      "id": "training_creep", "display_name": "訓練小兵",
      "hp": 100.0, "armor": 1.0, "magic_resistance": 0.0,
      "damage": 25.0, "attack_range": 50.0, "move_speed": 200.0,
      "enemy_type": "melee", "ai_type": "aggressive",
      "exp_reward": 5, "gold_reward": 12
    },
    {
      "id": "armored_dummy", "display_name": "裝甲假人",
      "hp": 200.0, "armor": 5.0, "magic_resistance": 0.0,
      "damage": 0.0, "attack_range": 0.0, "move_speed": 50.0,
      "enemy_type": "melee", "ai_type": "passive",
      "exp_reward": 0, "gold_reward": 20
    },
    {
      "id": "forest_ghost", "display_name": "森林幽靈",
      "hp": 150.0, "armor": 0.0, "magic_resistance": 10.0,
      "damage": 30.0, "attack_range": 50.0, "move_speed": 280.0,
      "enemy_type": "melee", "ai_type": "patrol",
      "exp_reward": 30, "gold_reward": 15
    },
    {
      "id": "wolf", "display_name": "野狼",
      "hp": 200.0, "armor": 2.0, "magic_resistance": 0.0,
      "damage": 45.0, "attack_range": 50.0, "move_speed": 350.0,
      "enemy_type": "melee", "ai_type": "berserker",
      "exp_reward": 40, "gold_reward": 20
    },
    {
      "id": "melee_minion", "display_name": "近戰兵",
      "hp": 550.0, "armor": 2.0, "magic_resistance": 5.0,
      "damage": 35.0, "attack_range": 50.0, "move_speed": 325.0,
      "enemy_type": "melee", "ai_type": "aggressive",
      "exp_reward": 60, "gold_reward": 36
    },
    {
      "id": "ranged_minion", "display_name": "遠程兵",
      "hp": 300.0, "armor": 0.0, "magic_resistance": 5.0,
      "damage": 25.0, "attack_range": 500.0, "move_speed": 325.0,
      "enemy_type": "ranged", "ai_type": "aggressive",
      "exp_reward": 60, "gold_reward": 36
    },
    {
      "id": "siege_minion", "display_name": "攻城兵",
      "hp": 800.0, "armor": 5.0, "magic_resistance": 5.0,
      "damage": 75.0, "attack_range": 200.0, "move_speed": 325.0,
      "enemy_type": "ranged", "ai_type": "aggressive",
      "exp_reward": 120, "gold_reward": 72
    },
    {
      "id": "saika_gunner", "display_name": "雜賀鐵炮兵",
      "hp": 400.0, "armor": 0.0, "magic_resistance": 0.0,
      "damage": 45.0, "attack_range": 600.0, "move_speed": 320.0,
      "enemy_type": "ranged", "ai_type": "aggressive",
      "exp_reward": 0, "gold_reward": 0
    },
    {
      "id": "sharpshooter", "display_name": "神射手",
      "hp": 350.0, "armor": 1.0, "magic_resistance": 0.0,
      "damage": 60.0, "attack_range": 800.0, "move_speed": 300.0,
      "enemy_type": "ranged", "ai_type": "aggressive",
      "exp_reward": 80, "gold_reward": 50
    },
    {
      "id": "td_stress", "display_name": "壓測怪",
      "hp": 10000000.0, "armor": 0.0, "magic_resistance": 0.0,
      "damage": 0.0, "attack_range": 0.0, "move_speed": 100.0,
      "enemy_type": "melee", "ai_type": "passive",
      "exp_reward": 0, "gold_reward": 0
    },
    {
      "id": "archmage_boss", "display_name": "大法師王",
      "hp": 1500.0, "armor": 3.0, "magic_resistance": 35.0,
      "damage": 85.0, "attack_range": 700.0, "move_speed": 300.0,
      "enemy_type": "boss", "ai_type": "aggressive",
      "exp_reward": 400, "gold_reward": 200
    },
    {
      "id": "wild_wolf", "display_name": "狂野野狼",
      "hp": 200.0, "armor": 2.0, "magic_resistance": 0.0,
      "damage": 45.0, "attack_range": 50.0, "move_speed": 350.0,
      "enemy_type": "melee", "ai_type": "berserker",
      "exp_reward": 40, "gold_reward": 20
    }
  ],

  "projectile_kinds": [
    { "id": "dart" },
    { "id": "spike_opult" },
    { "id": "tack" },
    { "id": "tack_blade" },
    { "id": "bomb" },
    { "id": "bomb_frag" },
    { "id": "saika_shot" },
    { "id": "ice" },
    { "id": "icicle" }
  ]
}
